boatmacro/__init__.py
boatmacro-3.0.dist-info/METADATA
boatmacro-3.0.dist-info/RECORD
boatmacro-3.0.dist-info/WHEEL
boatmacro-3.0.dist-info/top_level.txt
