Metadata-Version: 2.1
Name: boatmacro
Version: 3.0
Summary: auto | macro module
Home-page: https://github.com/boatio/boatmacro/
Author: boatonboat
Author-email: usbjewon@gmail.com
License: UNKNOWN
Platform: UNKNOWN
Classifier: Programming Language :: Python :: 3
Classifier: License :: OSI Approved :: MIT License
Classifier: Operating System :: OS Independent
